{
  "artifact_group_id": "S0048-011",
  "source_images": [
    "img_0124"
  ],
  "unique_pages": 1,
  "duplicate_pages_culled": 0,
  "item_type": "document_page",
  "subject": "New York State Teachers Association Program of Exercises",
  "location_guess": "Brooklyn, 1889",
  "notes": "Page from a program of exercises for the New York State Teachers Association held in Brooklyn in 1889, listing speakers and events.",
  "average_confidence": 0.951,
  "group_confidence": 0.5,
  "link_types": [
    "session_default"
  ],
  "confident_link_ratio": 0.0,
  "is_research": false
}